npi_registry_mcp/__init__.py
npi_registry_mcp/server.py
npi_registry_mcp_server-0.1.0.dist-info/METADATA
npi_registry_mcp_server-0.1.0.dist-info/WHEEL
npi_registry_mcp_server-0.1.0.dist-info/entry_points.txt
npi_registry_mcp_server-0.1.0.dist-info/licenses/LICENSE
npi_registry_mcp_server-0.1.0.dist-info/RECORD
