Metadata-Version: 2.4
Name: npi-registry-mcp-server
Version: 0.1.0
Summary: MCP server for searching the National Provider Identifier (NPI) registry
Project-URL: Homepage, https://github.com/eliotk/npi-registry-mcp-server
Project-URL: Repository, https://github.com/eliotk/npi-registry-mcp-server
Project-URL: Issues, https://github.com/eliotk/npi-registry-mcp-server/issues
Author-email: Eliot Kristan <eliot.k@gmail.com>
License: MIT
License-File: LICENSE
Classifier: Development Status :: 4 - Beta
Classifier: Intended Audience :: Developers
Classifier: License :: OSI Approved :: MIT License
Classifier: Programming Language :: Python :: 3
Classifier: Programming Language :: Python :: 3.10
Classifier: Programming Language :: Python :: 3.11
Classifier: Programming Language :: Python :: 3.12
Requires-Python: >=3.10
Requires-Dist: fastmcp>=0.2.0
Requires-Dist: httpx>=0.25.0
Requires-Dist: pydantic>=2.0.0
Provides-Extra: dev
Requires-Dist: black>=23.0.0; extra == 'dev'
Requires-Dist: isort>=5.12.0; extra == 'dev'
Requires-Dist: mypy>=1.5.0; extra == 'dev'
Requires-Dist: pytest-asyncio>=0.21.0; extra == 'dev'
Requires-Dist: pytest>=7.0.0; extra == 'dev'
Requires-Dist: ruff>=0.1.0; extra == 'dev'
